{"otherData": {},"traceEvents":[{"cat":"function","dur":1,"name":"void __cdecl Sandbox2D::OnDetach(void)","ph":"X","pid":0,"tid":2347985573,"ts":2538581321},{"cat":"function","dur":20,"name":"__cdecl Atlas::OpenGLTexture2D::~OpenGLTexture2D(void)","ph":"X","pid":0,"tid":2347985573,"ts":2538581410},{"cat":"function","dur":3159,"name":"void __cdecl Atlas::ImGuiLayer::OnDetach(void)","ph":"X","pid":0,"tid":2347985573,"ts":2538581476},{"cat":"function","dur":56266,"name":"void __cdecl Atlas::WindowsWindow::Shutdown(void)","ph":"X","pid":0,"tid":2347985573,"ts":2538584712},{"cat":"function","dur":56410,"name":"__cdecl Atlas::WindowsWindow::~WindowsWindow(void)","ph":"X","pid":0,"tid":2347985573,"ts":2538584712}]}