{"otherData": {},"traceEvents":[{"cat":"function","dur":33957,"name":"glfwInit","ph":"X","pid":0,"tid":2271677034,"ts":5447896342},{"cat":"function","dur":1840607,"name":"glfwCreateWindow","ph":"X","pid":0,"tid":2271677034,"ts":5447930443},{"cat":"function","dur":2858,"name":"void __cdecl Atlas::OpenGLContext::Init(void)","ph":"X","pid":0,"tid":2271677034,"ts":5449771169},{"cat":"function","dur":21,"name":"void __cdecl Atlas::WindowsWindow::SetVSync(bool)","ph":"X","pid":0,"tid":2271677034,"ts":5449774093},{"cat":"function","dur":1879852,"name":"void __cdecl Atlas::WindowsWindow::Init(const struct Atlas::WindowProps &)","ph":"X","pid":0,"tid":2271677034,"ts":5447894295},{"cat":"function","dur":1879870,"name":"__cdecl Atlas::WindowsWindow::WindowsWindow(const struct Atlas::WindowProps &)","ph":"X","pid":0,"tid":2271677034,"ts":5447894293},{"cat":"function","dur":22,"name":"void __cdecl Atlas::OpenGLRendererAPI::Init(void)","ph":"X","pid":0,"tid":2271677034,"ts":5449774203},{"cat":"function","dur":4,"name":"__cdecl Atlas::OpenGLVertexArray::OpenGLVertexArray(void)","ph":"X","pid":0,"tid":2271677034,"ts":5449774250},{"cat":"function","dur":221,"name":"__cdecl Atlas::OpenGLVertexBuffer::OpenGLVertexBuffer(float *,unsigned int)","ph":"X","pid":0,"tid":2271677034,"ts":5449774279},{"cat":"function","dur":0,"name":"void __cdecl Atlas::OpenGLVertexBuffer::Bind(void) const","ph":"X","pid":0,"tid":2271677034,"ts":5449774542},{"cat":"function","dur":29,"name":"void __cdecl Atlas::OpenGLVertexArray::AddVertexBuffer(const class std::shared_ptr<class Atlas::VertexBuffer> &)","ph":"X","pid":0,"tid":2271677034,"ts":5449774540},{"cat":"function","dur":5,"name":"__cdecl Atlas::OpenGLIndexBuffer::OpenGLIndexBuffer(unsigned int *,unsigned int)","ph":"X","pid":0,"tid":2271677034,"ts":5449774588},{"cat":"function","dur":0,"name":"void __cdecl Atlas::OpenGLIndexBuffer::Bind(void) const","ph":"X","pid":0,"tid":2271677034,"ts":5449774611},{"cat":"function","dur":17,"name":"void __cdecl Atlas::OpenGLVertexArray::SetIndexBuffer(const class std::shared_ptr<class Atlas::IndexBuffer> &)","ph":"X","pid":0,"tid":2271677034,"ts":5449774609},{"cat":"function","dur":126,"name":"__cdecl Atlas::OpenGLTexture2D::OpenGLTexture2D(unsigned int,unsigned int)","ph":"X","pid":0,"tid":2271677034,"ts":5449774645},{"cat":"function","dur":32,"name":"void __cdecl Atlas::OpenGLTexture2D::SetData(void *,unsigned int)","ph":"X","pid":0,"tid":2271677034,"ts":5449774792},{"cat":"function","dur":190,"name":"class std::basic_string<char,struct std::char_traits<char>,class std::allocator<char> > __cdecl Atlas::OpenGLShader::ReadFile(const class std::basic_string<char,struct std::char_traits<char>,class std::allocator<char> > &)","ph":"X","pid":0,"tid":2271677034,"ts":5449774849},{"cat":"function","dur":27,"name":"class std::unordered_map<unsigned int,class std::basic_string<char,struct std::char_traits<char>,class std::allocator<char> >,struct std::hash<unsigned int>,struct std::equal_to<unsigned int>,class std::allocator<struct std::pair<unsigned int const ,class std::basic_string<char,struct std::char_traits<char>,class std::allocator<char> > > > > __cdecl Atlas::OpenGLShader::PreProcess(const class std::basic_string<char,struct std::char_traits<char>,class std::allocator<char> > &)","ph":"X","pid":0,"tid":2271677034,"ts":5449775062},{"cat":"function","dur":244,"name":"void __cdecl Atlas::OpenGLShader::Compile(const class std::unordered_map<unsigned int,class std::basic_string<char,struct std::char_traits<char>,class std::allocator<char> >,struct std::hash<unsigned int>,struct std::equal_to<unsigned int>,class std::allocator<struct std::pair<unsigned int const ,class std::basic_string<char,struct std::char_traits<char>,class std::allocator<char> > > > > &)","ph":"X","pid":0,"tid":2271677034,"ts":5449775107},{"cat":"function","dur":530,"name":"__cdecl Atlas::OpenGLShader::OpenGLShader(const class std::basic_string<char,struct std::char_traits<char>,class std::allocator<char> > &)","ph":"X","pid":0,"tid":2271677034,"ts":5449774846},{"cat":"function","dur":8,"name":"void __cdecl Atlas::OpenGLShader::Bind(void) const","ph":"X","pid":0,"tid":2271677034,"ts":5449775393},{"cat":"function","dur":7,"name":"void __cdecl Atlas::OpenGLShader::SetInt(const class std::basic_string<char,struct std::char_traits<char>,class std::allocator<char> > &,int)","ph":"X","pid":0,"tid":2271677034,"ts":5449775449},{"cat":"function","dur":1228,"name":"void __cdecl Atlas::Renderer2D::Init(void)","ph":"X","pid":0,"tid":2271677034,"ts":5449774242},{"cat":"function","dur":1282,"name":"void __cdecl Atlas::Renderer::Init(void)","ph":"X","pid":0,"tid":2271677034,"ts":5449774202},{"cat":"function","dur":235,"name":"void __cdecl Atlas::ImGuiLayer::OnAttach(void)","ph":"X","pid":0,"tid":2271677034,"ts":5449775508},{"cat":"function","dur":268,"name":"void __cdecl Atlas::Application::PushOverlay(class Atlas::Layer *)","ph":"X","pid":0,"tid":2271677034,"ts":5449775502},{"cat":"function","dur":1881526,"name":"__cdecl Atlas::Application::Application(void)","ph":"X","pid":0,"tid":2271677034,"ts":5447894260},{"cat":"function","dur":1,"name":"__cdecl Atlas::OrthographicCamera::OrthographicCamera(float,float,float,float)","ph":"X","pid":0,"tid":2271677034,"ts":5449775809},{"cat":"function","dur":208,"name":"stbi_load - OpenGLTexture2D::OpenGLTexture2D(const std::string&) ","ph":"X","pid":0,"tid":2271677034,"ts":5449775831},{"cat":"function","dur":360,"name":"__cdecl Atlas::OpenGLTexture2D::OpenGLTexture2D(const class std::basic_string<char,struct std::char_traits<char>,class std::allocator<char> > &)","ph":"X","pid":0,"tid":2271677034,"ts":5449775831},{"cat":"function","dur":385,"name":"void __cdecl Sandbox2D::OnAttach(void)","ph":"X","pid":0,"tid":2271677034,"ts":5449775829},{"cat":"function","dur":403,"name":"void __cdecl Atlas::Application::PushLayer(class Atlas::Layer *)","ph":"X","pid":0,"tid":2271677034,"ts":5449775825}]}